{"mensajes":
    [
        {
            "mensaje":"GANAMOS JUSTICIA MÁS RÁPIDAMENTE SI HACEMOS JUSTICIA A LA PARTE CONTRARIA",
            "autor":"Mahatma Gandhi"
        },{
            "mensaje":"SI VIVIR SÓLO ES SOÑAR, HAGAMOS EL BIEN SOÑANDO",
            "autor":"Amado Neruo"
        },{
            "mensaje":"SI NO TIENES LA LIBERTAD INTERIOR, ¿QUÉ OTRA LIBERTAD ESPERAS PODER TENER?",
            "autor":"Arturo Graf"
        },{
            "mensaje":"HAY QUE LUCHAR, NADIE LLEGA A LA PERFECCIÓN POR MERA RENUNCIA.",
            "autor":"Mahabharata"
        },{
            "mensaje":"NO GASTES TU DINERO ANTES DE GANARLO.",
            "autor":"Thomas Jefferson"
        }
    ]
}